balltic/__init__.py
balltic/config.py
balltic/overrides.py
balltic/core/__init__.py
balltic/core/euler.py
balltic/core/gas.py
balltic/core/gpowder.py
balltic/core/grid.py
balltic/core/guns.py
balltic/gasdynamics/__init__.py
balltic/gasdynamics/gunpowder.py
balltic/gasdynamics/pneumatic.py
balltic/gd/__init__.py
balltic/gd/pneum.py
balltic/powders/__init__.py
examples/__init__.py
examples/gunpowder_cannon.py
examples/pneumatic_cannon.py
tests/__init__.py
tests/test_gpowder.py
tests/test_pneumatic.py
Balltic-0.2.0.dist-info/LICENCE
Balltic-0.2.0.dist-info/METADATA
Balltic-0.2.0.dist-info/WHEEL
Balltic-0.2.0.dist-info/top_level.txt
Balltic-0.2.0.dist-info/RECORD
