Metadata-Version: 2.1
Name: Balltic
Version: 0.2.0
Summary: Ballistics
Home-page: https://github.com/tohabyuraev/balltic
Author: Anthony Byuraev
Author-email: anthony.byuraev@gmail.com
License: BSD
Platform: UNKNOWN
Classifier: Intended Audience :: Science/Research
Classifier: Intended Audience :: Developers
Classifier: License :: OSI Approved :: BSD License
Classifier: Programming Language :: Python
Classifier: Programming Language :: Python :: 3
Classifier: Programming Language :: Python :: 3.6
Classifier: Programming Language :: Python :: 3.7
Classifier: Programming Language :: Python :: 3.8
Classifier: Topic :: Scientific/Engineering
Classifier: Operating System :: OS Independent
Requires-Python: >=3.6
Requires-Dist: numpy (==1.18.5)
